<?xml version="1.0" encoding="UTF-8" standalone="yes"?>
<trpDocMetadata>
    <docId>6489825</docId>
    <title>Akte_110.pdf</title>
    <uploadTimestamp>1737634155328</uploadTimestamp>
    <scriptType>NORMAL</scriptType>
    <uploader>mail@sven-burkhardt.de</uploader>
    <uploaderId>46641</uploaderId>
    <nrOfPages>1</nrOfPages>
    <pageId>89842025</pageId>
    <url>https://files.transkribus.eu/Get?fileType=view&amp;id=HUUZLCGOEBKHMRMNFQXUBVLJ</url>
    <thumbUrl>https://files.transkribus.eu/Get?fileType=thumb&amp;id=HUUZLCGOEBKHMRMNFQXUBVLJ</thumbUrl>
    <desc>privater Brief von Alfons an Spender</desc>
    <language></language>
    <status>0</status>
    <fimgStoreColl>TrpDoc_DEA_6489825</fimgStoreColl>
    <createdFromTimestamp>-941673600000</createdFromTimestamp>
    <origDocId>0</origDocId>
    <collectionList>
        <colList>
            <colId>1903711</colId>
            <colName>Maennerchor_Murg_Masterarbeit</colName>
            <description>created by mail@sven-burkhardt.de</description>
            <crowdsourcing>false</crowdsourcing>
            <elearning>false</elearning>
            <nrOfDocuments>0</nrOfDocuments>
            <isFavorite>false</isFavorite>
        </colList>
    </collectionList>
    <mainColId>1903711</mainColId>
</trpDocMetadata>
